memory/__init__.py
timem/__init__.py
timem/async_client.py
timem/circuit_breaker.py
timem/cli.py
timem/client.py
timem/connection_pool.py
timem/enhanced_async_client.py
timem/exceptions.py
timem/memory.py
timem/monitoring.py
timem/sync_client.py
timem/resources/__init__.py
timem/resources/optimization.py
timem/resources/resume.py
timem/resources/session.py
timem/types/__init__.py
timem/types/optimization.py
timem/types/resume.py
timem/types/session.py
timem_ai-0.1.1.dist-info/licenses/LICENSE
timem_ai-0.1.1.dist-info/METADATA
timem_ai-0.1.1.dist-info/WHEEL
timem_ai-0.1.1.dist-info/entry_points.txt
timem_ai-0.1.1.dist-info/top_level.txt
timem_ai-0.1.1.dist-info/RECORD
