Metadata-Version: 2.4
Name: timem-ai
Version: 0.1.1
Summary: TiMEM Python SDK - Time-based Memory Management and Experience Learning toolkit | TiMEM Python SDK - 时间记忆管理与经验学习工具包
Home-page: https://github.com/AIGility-Cloud-Innovation/timem-python
Author: AIGility Cloud Innovation
Author-email: AIGility Cloud Innovation <contact@aigility.com>
Maintainer-email: AIGility Cloud Innovation <contact@aigility.com>
License: MIT
Project-URL: Homepage, https://github.com/AIGility-Cloud-Innovation/timem-python
Project-URL: Documentation, https://timem-python.readthedocs.io
Project-URL: Repository, https://github.com/AIGility-Cloud-Innovation/timem-python
Project-URL: Issues, https://github.com/AIGility-Cloud-Innovation/timem-python/issues
Project-URL: Changelog, https://github.com/AIGility-Cloud-Innovation/timem-python/blob/main/CHANGELOG.md
Keywords: timem,memory,experience-learning,rule-engine,user-profile,ai,machine-learning
Classifier: Development Status :: 4 - Beta
Classifier: Intended Audience :: Developers
Classifier: License :: OSI Approved :: MIT License
Classifier: Operating System :: OS Independent
Classifier: Programming Language :: Python :: 3
Classifier: Programming Language :: Python :: 3.8
Classifier: Programming Language :: Python :: 3.9
Classifier: Programming Language :: Python :: 3.10
Classifier: Programming Language :: Python :: 3.11
Classifier: Programming Language :: Python :: 3.12
Classifier: Topic :: Software Development :: Libraries :: Python Modules
Classifier: Topic :: Scientific/Engineering :: Artificial Intelligence
Classifier: Topic :: Database :: Database Engines/Servers
Requires-Python: >=3.8
License-File: LICENSE
Requires-Dist: httpx>=0.24.0
Requires-Dist: pydantic>=2.0.0
Requires-Dist: typing-extensions>=4.0.0
Provides-Extra: dev
Requires-Dist: pytest>=7.0.0; extra == "dev"
Requires-Dist: pytest-asyncio>=0.21.0; extra == "dev"
Requires-Dist: pytest-cov>=4.0.0; extra == "dev"
Requires-Dist: black>=22.0.0; extra == "dev"
Requires-Dist: isort>=5.0.0; extra == "dev"
Requires-Dist: flake8>=5.0.0; extra == "dev"
Requires-Dist: mypy>=1.0.0; extra == "dev"
Requires-Dist: pre-commit>=2.20.0; extra == "dev"
Provides-Extra: docs
Requires-Dist: sphinx>=5.0.0; extra == "docs"
Requires-Dist: sphinx-rtd-theme>=1.0.0; extra == "docs"
Requires-Dist: myst-parser>=0.18.0; extra == "docs"
Dynamic: author
Dynamic: home-page
Dynamic: license-file
Dynamic: requires-python
